shopping/__init__.py
shopping/config.py
shopping/elk.py
shopping/get_tweepy.py
shopping/preprocess.py
shopping/scripts.py
sysnet_shopping-1.0.6.dist-info/LICENSE.md
sysnet_shopping-1.0.6.dist-info/METADATA
sysnet_shopping-1.0.6.dist-info/WHEEL
sysnet_shopping-1.0.6.dist-info/top_level.txt
sysnet_shopping-1.0.6.dist-info/RECORD
