Metadata-Version: 2.1
Name: sysnet-shopping
Version: 1.0.6
Summary: Data mining shopping portals
Author-email: Data Miner <info@sysnet.cz>
License: # LICENCE PRO DOMÁCÍ POUŽITÍ (SYSNET Home Use License) v 1.0
Project-URL: Homepage, https://github.com/SYSNET-CZ/mining/tree/main/shopping
Classifier: Programming Language :: Python :: 3
Classifier: License :: Free For Home Use
Classifier: Operating System :: OS Independent
Classifier: Topic :: Database :: Front-Ends
Requires-Python: >=3.7
License-File: LICENSE.md
